{
  "relative_path": "VALORANT_01-18-2026_2-27-15-982/VALORANT 01-18-2026 2-54-28-188.mp4",
  "generated_at_utc": "2026-03-13T17:22:26.372441+00:00",
  "metadata": {
    "title": "Calm Aim and Quick Reactions Secure a Clean Double Kill in VALORANT",
    "description": "Check out this fast-paced clip where smart timing and steady aim make the difference in a 2v1. Notice how smooth peeks and positioning help close out the round quickly.\nWhat’s your favorite spot to clutch in VALORANT?\n\n#shorts #valorant #gaming\n\nShare your best clutch moments in the comments!\n\n#shorts #valorant #gaming #clutch #fps",
    "tags": [
      "valorant",
      "valorant clips",
      "valorant double kill",
      "gaming",
      "fps",
      "clutch plays",
      "shorts",
      "valorant gameplay",
      "quick reaction",
      "smart positioning",
      "aim training",
      "multiplayer",
      "competitive gaming",
      "shooter",
      "esports"
    ],
    "hashtags": [
      "#shorts",
      "#valorant",
      "#gaming",
      "#clutch",
      "#fps"
    ],
    "cta": "Share your best clutch moments in the comments!"
  }
}