{
  "relative_path": "VALORANT_01-16-2026_0-07-34-067/VALORANT 01-16-2026 0-11-57-705.mp4",
  "generated_at_utc": "2026-03-11T15:52:25.866492+00:00",
  "metadata": {
    "title": "Turning a 2v1 Mid Fight With Sharp Timing and Clean Headshots in VALORANT",
    "description": "Watch this intense 2v1 fight unfold on mid. Notice the perfect timing and precise shots that change the round. What’s your favorite clutch spot on mid?\n\nGot a clutch like this? Share your best plays in the comments!\n\n#shorts #valorant #gaming #clutch #fps",
    "tags": [
      "valorant",
      "valorant clips",
      "valorant 2v1",
      "fps",
      "gaming",
      "valorant mid",
      "shorts",
      "clutch plays",
      "headshots",
      "timing",
      "positioning",
      "competitive gaming",
      "valorant clutch",
      "quick reflexes",
      "gameplay"
    ],
    "hashtags": [
      "#shorts",
      "#valorant",
      "#gaming",
      "#clutch",
      "#fps"
    ],
    "cta": "Got a clutch like this? Share your best plays in the comments!"
  }
}