{
  "relative_path": "VALORANT_01-03-2026_16-03-59-277/VALORANT 01-03-2026 16-16-46-604.mp4",
  "generated_at_utc": "2026-03-05T17:00:53.787536+00:00",
  "metadata": {
    "title": "Intense VALORANT Clutch Moment in Competitive Match | Quick FPS Action | 01-03 16:16:46",
    "description": "Watch this fast-paced VALORANT clip showcasing sharp aiming and smart plays. Perfect for fans of competitive FPS games. Stay tuned for more exciting shorts!\n\nSubscribe for more thrilling VALORANT highlights and gameplay shorts!\n\n#shorts #valorant #gaming #fps #clutch\n\nSource clip: VALORANT 01-03-2026 16-16-46-604",
    "tags": [
      "valorant",
      "valorant clips",
      "valorant gameplay",
      "gaming",
      "fps",
      "competitive gaming",
      "shooter",
      "valorant highlights",
      "short clips",
      "fast reaction",
      "clutch moments",
      "gaming shorts",
      "tactical shooter",
      "esports",
      "fps gameplay"
    ],
    "hashtags": [
      "#shorts",
      "#valorant",
      "#gaming",
      "#fps",
      "#clutch"
    ],
    "cta": "Subscribe for more thrilling VALORANT highlights and gameplay shorts!"
  },
  "kills": 0,
  "agent_name": "Unknown",
  "kill_events": [],
  "analysis_generated_at_utc": "2026-03-07T07:16:33.614097+00:00",
  "kill_event_details": [],
  "analysis_method": "fixed_roi_kill_banner_feed_v2"
}